xbus/__init__.py
xbus/monitor/i18n.py
xbus/monitor/__init__.py
xbus/monitor/aiozmq_util.py
xbus/monitor/consumers.py
xbus/monitor/auth.py
xbus/monitor/statichome.py
xbus/monitor/core.py
xbus/monitor/resources/__init__.py
xbus/monitor/resources/root.py
xbus/monitor/resources/records.py
xbus/monitor/resources/data_clearing/collections.py
xbus/monitor/resources/data_clearing/__init__.py
xbus/monitor/resources/data_clearing/records.py
xbus/monitor/resources/monitor/collections.py
xbus/monitor/resources/monitor/__init__.py
xbus/monitor/resources/monitor/records.py
xbus/monitor/utils/__init__.py
xbus/monitor/utils/singleton.py
xbus/monitor/utils/config.py
xbus/monitor/utils/xml_config.py
xbus/monitor/views/saml2_login.py
xbus/monitor/views/__init__.py
xbus/monitor/views/util.py
xbus/monitor/views/http_login.py
xbus/monitor/views/login_info.py
xbus/monitor/views/xml_config.py
xbus/monitor/views/api/cl_item_column.py
xbus/monitor/views/api/cl_event_type.py
xbus/monitor/views/api/upload.py
xbus/monitor/views/api/envelope.py
xbus/monitor/views/api/cl_item_join.py
xbus/monitor/views/api/event_error_tracking.py
xbus/monitor/views/api/emitter_profile.py
xbus/monitor/views/api/input_descriptor.py
xbus/monitor/views/api/service.py
xbus/monitor/views/api/__init__.py
xbus/monitor/views/api/util.py
xbus/monitor/views/api/replay_envelope.py
xbus/monitor/views/api/consumer.py
xbus/monitor/views/api/role.py
xbus/monitor/views/api/event_node.py
xbus/monitor/views/api/event_tracking.py
xbus/monitor/views/api/emitter.py
xbus/monitor/views/api/user.py
xbus/monitor/views/api/cl_item_type.py
xbus/monitor/views/api/emission_profile.py
xbus/monitor/views/api/event_error.py
xbus/monitor/views/api/event.py
xbus/monitor/views/api/event_type.py
xbus/monitor/views/api/cl_item.py
xbus/monitor/views/api/view_decorators.py
xbus/monitor/views/api/xml_config.py
xbus/monitor/scripts/__init__.py
xbus/monitor/scripts/func.sql
xbus.monitor-0.2.0.dist-info/metadata.json
xbus.monitor-0.2.0.dist-info/METADATA
xbus.monitor-0.2.0.dist-info/entry_points.txt
xbus.monitor-0.2.0.dist-info/WHEEL
xbus.monitor-0.2.0.dist-info/top_level.txt
xbus.monitor-0.2.0.dist-info/DESCRIPTION.rst
xbus.monitor-0.2.0.dist-info/RECORD
