Metadata-Version: 2.0
Name: xbus.monitor
Version: 0.2.0
Summary: Web app to configure and monitor Xbus
Home-page: http://xbus.io
Author: XCG
Author-email: contact@xcg-consulting.fr
License: UNKNOWN
Keywords: xbus monitor web pyramid
Platform: UNKNOWN
Classifier: Programming Language :: Python
Classifier: Framework :: Pyramid
Classifier: Intended Audience :: Developers
Classifier: Intended Audience :: Financial and Insurance Industry
Classifier: Intended Audience :: Information Technology
Classifier: Intended Audience :: Other Audience
Classifier: Intended Audience :: Science/Research
Classifier: Intended Audience :: System Administrators
Classifier: License :: OSI Approved :: MIT License
Classifier: Operating System :: OS Independent
Classifier: Programming Language :: Python :: 3.4
Classifier: Topic :: Internet :: WWW/HTTP
Classifier: Topic :: Internet :: WWW/HTTP :: WSGI :: Application
Requires-Dist: aiopg (==0.5.1)
Requires-Dist: msgpack-python (==0.4.3)
Requires-Dist: psycopg2 (==2.5.4)
Requires-Dist: pyramid
Requires-Dist: pyramid-chameleon
Requires-Dist: pyramid-debugtoolbar
Requires-Dist: pyramid-httpauth
Requires-Dist: pyramid-redis-sessions
Requires-Dist: pyramid-tm
Requires-Dist: pyzmq (==14.4.1)
Requires-Dist: redis (>2.9.1)
Requires-Dist: six
Requires-Dist: SQLAlchemy (==0.9.8)
Requires-Dist: transaction
Requires-Dist: waitress
Requires-Dist: xbus.broker (>=0.2.0)
Requires-Dist: xbus.file-emitter
Requires-Dist: zope.sqlalchemy (==0.7.5)
